ulid_rs-0.1.3.dist-info/METADATA
ulid_rs-0.1.3.dist-info/WHEEL
ulid_rs/__init__.py
ulid_rs/ulid_rs.cpython-37m-darwin.so
ulid_rs-0.1.3.dist-info/RECORD
