Metadata-Version: 2.1
Name: ulid-rs
Version: 0.1.3
Classifier: Programming Language :: Rust
Classifier: Programming Language :: Python :: Implementation :: CPython
Classifier: Programming Language :: Python :: Implementation :: PyPy
Requires-Python: >=3.7
Project-URL: repository, https://github.com/smallverse/ulid-rs
